dscin_ppy/__init__.py
dscin_ppy/aws_utils.py
dscin_ppy/constants.py
dscin_ppy/data_extracts.py
dscin_ppy/db_utils.py
dscin_ppy/errors.py
dscin_ppy/etl_job.py
dscin_ppy/exposing_reports.py
dscin_ppy/forecasting_app.py
dscin_ppy/functions.py
dscin_ppy/job_parameters.py
dscin_ppy/utils.py
dscin_ppy-0.0.20.dist-info/METADATA
dscin_ppy-0.0.20.dist-info/WHEEL
dscin_ppy-0.0.20.dist-info/top_level.txt
dscin_ppy-0.0.20.dist-info/RECORD
