Metadata-Version: 2.1
Name: dscin_ppy
Version: 0.0.20
Summary: Collection of utility functions
Author: Andrea Chiappo
Author-email: chiappo.andrea@gmail.com
Requires-Dist: scipy==1.10.1
Requires-Dist: pandas==2.0.1
Requires-Dist: numpy==1.23.5
Requires-Dist: s3fs==2022.11.0
Requires-Dist: hdbcli==2.19.21
Requires-Dist: s3transfer==0.6.1
